Workbook

Sheet Assumptions
A1: FreshGo Retail — Tier-2 Quick-Commerce Entry
A2: Key Assumptions (edit yellow cells)
A4: Assumption | B4: Value | C4: Source / Note
A5: Average Order Value (AOV) | B5: 550 | C5: ₹/order — Chiratae Ventures: viable AOV band ₹500-700 for QC breakeven
A6: Gross margin on goods sold | B6: 0.18 | C6: % of AOV — typical Indian grocery/QC blended margin 15-20%
A7: Variable cost per order (delivery + packing) | B7: 45 | C7: ₹/order — industry range ₹40-50/order for last-mile in Tier-2/3
A8: Fixed cost per dark store per month | B8: 450000 | C8: ₹ — rent + staff + utilities + refrigeration, Tier-2 city estimate
A9: Store buildout / setup cost (one-time) | B9: 900000 | C9: ₹ — fit-out, racking, refrigeration, tech, initial inventory
A10: Month 1 daily order volume | B10: 120 | C10: orders/day — conservative Tier-2 launch ramp
A11: Month 12 target daily order volume | B11: 500 | C11: orders/day — vs. non-metro average ~850/day per Redseer; phased target
A12: Month 24 target daily order volume | B12: 900 | C12: orders/day — approaching non-metro breakeven range
A13: Days per month | B13: 30 | C13: for monthly order volume calculation
A14: Number of dark stores in Wave 1 pilot | B14: 10 | C14: cities selected per prioritization criteria (see deck)
A16: Sources: Chiratae Ventures QC dark-store economics note (2025); Redseer dark-store OPD/breakeven analysis (Feb 2026); Business Model Hub cost-per-order range (Apr 2026); ResearchAndMarkets India Quick Commerce Databook Q1 2026.

Sheet Store Breakeven Model
A1: Single Dark Store — 24-Month Breakeven Model
A2: Orders/day ramps linearly Month 1 → Month 12 → Month 24 (see Assumptions)
A4: Month | B4: Orders/Day | C4: Orders/Month | D4: Revenue (₹) | E4: Gross Profit (₹) | F4: Variable Cost (₹) | G4: Contribution Margin (₹) | H4: Fixed Cost (₹) | I4: Monthly Net (₹) | J4: Cumulative Net incl. Setup (₹)
A5: 1 | B5: =Assumptions!$B$10+(Assumptions!$B$11-Assumptions!$B$10)*(A5-1)/11 -> 120 | C5: =B5*Assumptions!$B$13 -> 3600 | D5: =C5*Assumptions!$B$5 -> 1980000 | E5: =D5*Assumptions!$B$6 -> 356400 | F5: =C5*Assumptions!$B$7 -> 162000 | G5: =E5-F5 -> 194400 | H5: =Assumptions!$B$8 -> 450000 | I5: =G5-H5 -> -255600 | J5: =I5-Assumptions!$B$9 -> -1155600
A6: 2 | B6: =Assumptions!$B$10+(Assumptions!$B$11-Assumptions!$B$10)*(A6-1)/11 -> 154.54545 | C6: =B6*Assumptions!$B$13 -> 4636.3636 | D6: =C6*Assumptions!$B$5 -> 2550000 | E6: =D6*Assumptions!$B$6 -> 459000 | F6: =C6*Assumptions!$B$7 -> 208636.36 | G6: =E6-F6 -> 250363.64 | H6: =Assumptions!$B$8 -> 450000 | I6: =G6-H6 -> -199636.36 | J6: =J5+I6 -> -1355236.4
A7: 3 | B7: =Assumptions!$B$10+(Assumptions!$B$11-Assumptions!$B$10)*(A7-1)/11 -> 189.09091 | C7: =B7*Assumptions!$B$13 -> 5672.7273 | D7: =C7*Assumptions!$B$5 -> 3120000 | E7: =D7*Assumptions!$B$6 -> 561600 | F7: =C7*Assumptions!$B$7 -> 255272.73 | G7: =E7-F7 -> 306327.27 | H7: =Assumptions!$B$8 -> 450000 | I7: =G7-H7 -> -143672.73 | J7: =J6+I7 -> -1498909.1
A8: 4 | B8: =Assumptions!$B$10+(Assumptions!$B$11-Assumptions!$B$10)*(A8-1)/11 -> 223.63636 | C8: =B8*Assumptions!$B$13 -> 6709.0909 | D8: =C8*Assumptions!$B$5 -> 3690000 | E8: =D8*Assumptions!$B$6 -> 664200 | F8: =C8*Assumptions!$B$7 -> 301909.09 | G8: =E8-F8 -> 362290.91 | H8: =Assumptions!$B$8 -> 450000 | I8: =G8-H8 -> -87709.091 | J8: =J7+I8 -> -1586618.2
A9: 5 | B9: =Assumptions!$B$10+(Assumptions!$B$11-Assumptions!$B$10)*(A9-1)/11 -> 258.18182 | C9: =B9*Assumptions!$B$13 -> 7745.4545 | D9: =C9*Assumptions!$B$5 -> 4260000 | E9: =D9*Assumptions!$B$6 -> 766800 | F9: =C9*Assumptions!$B$7 -> 348545.45 | G9: =E9-F9 -> 418254.55 | H9: =Assumptions!$B$8 -> 450000 | I9: =G9-H9 -> -31745.455 | J9: =J8+I9 -> -1618363.6
A10: 6 | B10: =Assumptions!$B$10+(Assumptions!$B$11-Assumptions!$B$10)*(A10-1)/11 -> 292.72727 | C10: =B10*Assumptions!$B$13 -> 8781.8182 | D10: =C10*Assumptions!$B$5 -> 4830000 | E10: =D10*Assumptions!$B$6 -> 869400 | F10: =C10*Assumptions!$B$7 -> 395181.82 | G10: =E10-F10 -> 474218.18 | H10: =Assumptions!$B$8 -> 450000 | I10: =G10-H10 -> 24218.182 | J10: =J9+I10 -> -1594145.5
A11: 7 | B11: =Assumptions!$B$10+(Assumptions!$B$11-Assumptions!$B$10)*(A11-1)/11 -> 327.27273 | C11: =B11*Assumptions!$B$13 -> 9818.1818 | D11: =C11*Assumptions!$B$5 -> 5400000 | E11: =D11*Assumptions!$B$6 -> 972000 | F11: =C11*Assumptions!$B$7 -> 441818.18 | G11: =E11-F11 -> 530181.82 | H11: =Assumptions!$B$8 -> 450000 | I11: =G11-H11 -> 80181.818 | J11: =J10+I11 -> -1513963.6
A12: 8 | B12: =Assumptions!$B$10+(Assumptions!$B$11-Assumptions!$B$10)*(A12-1)/11 -> 361.81818 | C12: =B12*Assumptions!$B$13 -> 10854.545 | D12: =C12*Assumptions!$B$5 -> 5970000 | E12: =D12*Assumptions!$B$6 -> 1074600 | F12: =C12*Assumptions!$B$7 -> 488454.55 | G12: =E12-F12 -> 586145.45 | H12: =Assumptions!$B$8 -> 450000 | I12: =G12-H12 -> 136145.45 | J12: =J11+I12 -> -1377818.2
A13: 9 | B13: =Assumptions!$B$10+(Assumptions!$B$11-Assumptions!$B$10)*(A13-1)/11 -> 396.36364 | C13: =B13*Assumptions!$B$13 -> 11890.909 | D13: =C13*Assumptions!$B$5 -> 6540000 | E13: =D13*Assumptions!$B$6 -> 1177200 | F13: =C13*Assumptions!$B$7 -> 535090.91 | G13: =E13-F13 -> 642109.09 | H13: =Assumptions!$B$8 -> 450000 | I13: =G13-H13 -> 192109.09 | J13: =J12+I13 -> -1185709.1
A14: 10 | B14: =Assumptions!$B$10+(Assumptions!$B$11-Assumptions!$B$10)*(A14-1)/11 -> 430.90909 | C14: =B14*Assumptions!$B$13 -> 12927.273 | D14: =C14*Assumptions!$B$5 -> 7110000 | E14: =D14*Assumptions!$B$6 -> 1279800 | F14: =C14*Assumptions!$B$7 -> 581727.27 | G14: =E14-F14 -> 698072.73 | H14: =Assumptions!$B$8 -> 450000 | I14: =G14-H14 -> 248072.73 | J14: =J13+I14 -> -937636.36
A15: 11 | B15: =Assumptions!$B$10+(Assumptions!$B$11-Assumptions!$B$10)*(A15-1)/11 -> 465.45455 | C15: =B15*Assumptions!$B$13 -> 13963.636 | D15: =C15*Assumptions!$B$5 -> 7680000 | E15: =D15*Assumptions!$B$6 -> 1382400 | F15: =C15*Assumptions!$B$7 -> 628363.64 | G15: =E15-F15 -> 754036.36 | H15: =Assumptions!$B$8 -> 450000 | I15: =G15-H15 -> 304036.36 | J15: =J14+I15 -> -633600
A16: 12 | B16: =Assumptions!$B$10+(Assumptions!$B$11-Assumptions!$B$10)*(A16-1)/11 -> 500 | C16: =B16*Assumptions!$B$13 -> 15000 | D16: =C16*Assumptions!$B$5 -> 8250000 | E16: =D16*Assumptions!$B$6 -> 1485000 | F16: =C16*Assumptions!$B$7 -> 675000 | G16: =E16-F16 -> 810000 | H16: =Assumptions!$B$8 -> 450000 | I16: =G16-H16 -> 360000 | J16: =J15+I16 -> -273600
A17: 13 | B17: =Assumptions!$B$11+(Assumptions!$B$12-Assumptions!$B$11)*(A17-12)/12 -> 533.33333 | C17: =B17*Assumptions!$B$13 -> 16000 | D17: =C17*Assumptions!$B$5 -> 8800000 | E17: =D17*Assumptions!$B$6 -> 1584000 | F17: =C17*Assumptions!$B$7 -> 720000 | G17: =E17-F17 -> 864000 | H17: =Assumptions!$B$8 -> 450000 | I17: =G17-H17 -> 414000 | J17: =J16+I17 -> 140400
A18: 14 | B18: =Assumptions!$B$11+(Assumptions!$B$12-Assumptions!$B$11)*(A18-12)/12 -> 566.66667 | C18: =B18*Assumptions!$B$13 -> 17000 | D18: =C18*Assumptions!$B$5 -> 9350000 | E18: =D18*Assumptions!$B$6 -> 1683000 | F18: =C18*Assumptions!$B$7 -> 765000 | G18: =E18-F18 -> 918000 | H18: =Assumptions!$B$8 -> 450000 | I18: =G18-H18 -> 468000 | J18: =J17+I18 -> 608400
A19: 15 | B19: =Assumptions!$B$11+(Assumptions!$B$12-Assumptions!$B$11)*(A19-12)/12 -> 600 | C19: =B19*Assumptions!$B$13 -> 18000 | D19: =C19*Assumptions!$B$5 -> 9900000 | E19: =D19*Assumptions!$B$6 -> 1782000 | F19: =C19*Assumptions!$B$7 -> 810000 | G19: =E19-F19 -> 972000 | H19: =Assumptions!$B$8 -> 450000 | I19: =G19-H19 -> 522000 | J19: =J18+I19 -> 1130400
A20: 16 | B20: =Assumptions!$B$11+(Assumptions!$B$12-Assumptions!$B$11)*(A20-12)/12 -> 633.33333 | C20: =B20*Assumptions!$B$13 -> 19000 | D20: =C20*Assumptions!$B$5 -> 10450000 | E20: =D20*Assumptions!$B$6 -> 1881000 | F20: =C20*Assumptions!$B$7 -> 855000 | G20: =E20-F20 -> 1026000 | H20: =Assumptions!$B$8 -> 450000 | I20: =G20-H20 -> 576000 | J20: =J19+I20 -> 1706400
A21: 17 | B21: =Assumptions!$B$11+(Assumptions!$B$12-Assumptions!$B$11)*(A21-12)/12 -> 666.66667 | C21: =B21*Assumptions!$B$13 -> 20000 | D21: =C21*Assumptions!$B$5 -> 11000000 | E21: =D21*Assumptions!$B$6 -> 1980000 | F21: =C21*Assumptions!$B$7 -> 900000 | G21: =E21-F21 -> 1080000 | H21: =Assumptions!$B$8 -> 450000 | I21: =G21-H21 -> 630000 | J21: =J20+I21 -> 2336400
A22: 18 | B22: =Assumptions!$B$11+(Assumptions!$B$12-Assumptions!$B$11)*(A22-12)/12 -> 700 | C22: =B22*Assumptions!$B$13 -> 21000 | D22: =C22*Assumptions!$B$5 -> 11550000 | E22: =D22*Assumptions!$B$6 -> 2079000 | F22: =C22*Assumptions!$B$7 -> 945000 | G22: =E22-F22 -> 1134000 | H22: =Assumptions!$B$8 -> 450000 | I22: =G22-H22 -> 684000 | J22: =J21+I22 -> 3020400
A23: 19 | B23: =Assumptions!$B$11+(Assumptions!$B$12-Assumptions!$B$11)*(A23-12)/12 -> 733.33333 | C23: =B23*Assumptions!$B$13 -> 22000 | D23: =C23*Assumptions!$B$5 -> 12100000 | E23: =D23*Assumptions!$B$6 -> 2178000 | F23: =C23*Assumptions!$B$7 -> 990000 | G23: =E23-F23 -> 1188000 | H23: =Assumptions!$B$8 -> 450000 | I23: =G23-H23 -> 738000 | J23: =J22+I23 -> 3758400
A24: 20 | B24: =Assumptions!$B$11+(Assumptions!$B$12-Assumptions!$B$11)*(A24-12)/12 -> 766.66667 | C24: =B24*Assumptions!$B$13 -> 23000 | D24: =C24*Assumptions!$B$5 -> 12650000 | E24: =D24*Assumptions!$B$6 -> 2277000 | F24: =C24*Assumptions!$B$7 -> 1035000 | G24: =E24-F24 -> 1242000 | H24: =Assumptions!$B$8 -> 450000 | I24: =G24-H24 -> 792000 | J24: =J23+I24 -> 4550400
A25: 21 | B25: =Assumptions!$B$11+(Assumptions!$B$12-Assumptions!$B$11)*(A25-12)/12 -> 800 | C25: =B25*Assumptions!$B$13 -> 24000 | D25: =C25*Assumptions!$B$5 -> 13200000 | E25: =D25*Assumptions!$B$6 -> 2376000 | F25: =C25*Assumptions!$B$7 -> 1080000 | G25: =E25-F25 -> 1296000 | H25: =Assumptions!$B$8 -> 450000 | I25: =G25-H25 -> 846000 | J25: =J24+I25 -> 5396400
A26: 22 | B26: =Assumptions!$B$11+(Assumptions!$B$12-Assumptions!$B$11)*(A26-12)/12 -> 833.33333 | C26: =B26*Assumptions!$B$13 -> 25000 | D26: =C26*Assumptions!$B$5 -> 13750000 | E26: =D26*Assumptions!$B$6 -> 2475000 | F26: =C26*Assumptions!$B$7 -> 1125000 | G26: =E26-F26 -> 1350000 | H26: =Assumptions!$B$8 -> 450000 | I26: =G26-H26 -> 900000 | J26: =J25+I26 -> 6296400
A27: 23 | B27: =Assumptions!$B$11+(Assumptions!$B$12-Assumptions!$B$11)*(A27-12)/12 -> 866.66667 | C27: =B27*Assumptions!$B$13 -> 26000 | D27: =C27*Assumptions!$B$5 -> 14300000 | E27: =D27*Assumptions!$B$6 -> 2574000 | F27: =C27*Assumptions!$B$7 -> 1170000 | G27: =E27-F27 -> 1404000 | H27: =Assumptions!$B$8 -> 450000 | I27: =G27-H27 -> 954000 | J27: =J26+I27 -> 7250400
A28: 24 | B28: =Assumptions!$B$11+(Assumptions!$B$12-Assumptions!$B$11)*(A28-12)/12 -> 900 | C28: =B28*Assumptions!$B$13 -> 27000 | D28: =C28*Assumptions!$B$5 -> 14850000 | E28: =D28*Assumptions!$B$6 -> 2673000 | F28: =C28*Assumptions!$B$7 -> 1215000 | G28: =E28-F28 -> 1458000 | H28: =Assumptions!$B$8 -> 450000 | I28: =G28-H28 -> 1008000 | J28: =J27+I28 -> 8258400
A30: Estimated payback month (cumulative net turns positive): | G30: =IFERROR(INDEX(A5:A28,MATCH(TRUE(),INDEX(J5:J28>0,0),0)),"beyond 24 months") -> 13

Sheet Portfolio Rollout Summary
A1: Wave 1 Pilot — Portfolio Summary (10 Dark Stores)
A2: Assumes staggered launch: 1 store every 6 weeks; each store follows the single-store ramp
A4: Metric | B4: Value
A5: Total setup capex (10 stores) | B5: =Assumptions!$B$9*Assumptions!$B$14 -> 9000000
A6: Steady-state monthly contribution margin per store (Month 24) | B6: ='Store Breakeven Model'!G28 -> 1458000
A7: Steady-state portfolio monthly contribution margin (10 stores) | B7: =B6*Assumptions!$B$14 -> 14580000
A8: Single-store payback period | B8: ='Store Breakeven Model'!G30 -> 13
A9: Recommended Wave 1 city count | B9: =Assumptions!$B$14 -> 10
A11: Note: This is an illustrative model built on publicly available industry benchmarks (not company-reported financials) to test entry feasibility directionally. Actual figures would require primary due diligence with real estate, staffing, and demand data.
